MANIFEST.in
README
setup.py
tox.ini
pytest_couchdbkit/__init__.py
pytest_couchdbkit/dumper.py
pytest_couchdbkit/hookspec.py
pytest_couchdbkit/utils.py
pytest_couchdbkit.egg-info/PKG-INFO
pytest_couchdbkit.egg-info/SOURCES.txt
pytest_couchdbkit.egg-info/dependency_links.txt
pytest_couchdbkit.egg-info/entry_points.txt
pytest_couchdbkit.egg-info/requires.txt
pytest_couchdbkit.egg-info/top_level.txt
testing/__init__.py
testing/test_dumper.py
testing/test_hooks.py
testing/test_utils.py