Metadata-Version: 1.0
Name: pytest-couchdbkit
Version: 0.5.1
Summary: py.test extension for per-test couchdb databases using couchdbkit
Home-page: http://bitbucket.org/RonnyPfannschmidt/pytest-couchdbkit
Author: RonnyPfannschmidt
Author-email: ronny.pfannschmidt@gmx.de
License: UNKNOWN
Platform: UNKNOWN
